datetime_selenium/__init__.py
datetime_selenium-0.0.0.dist-info/LICENSE
datetime_selenium-0.0.0.dist-info/METADATA
datetime_selenium-0.0.0.dist-info/WHEEL
datetime_selenium-0.0.0.dist-info/top_level.txt
datetime_selenium-0.0.0.dist-info/RECORD
