Metadata-Version: 2.1
Name: datetime-selenium
Version: 0.0.0
Summary: Send and receive datetime objects from web forms.
Home-page: https://dsbowen.github.io/datetime-selenium
Author: Dillon Bowen
Author-email: dsbowen@wharton.upenn.edu
License: UNKNOWN
Platform: UNKNOWN
Classifier: Programming Language :: Python :: 3
Classifier: License :: OSI Approved :: MIT License
Classifier: Operating System :: OS Independent
Requires-Python: >=3.6
Requires-Dist: selenium (>=3.141.0)
